pknulms.py
pknulms-1.0.2.dist-info/DESCRIPTION.rst
pknulms-1.0.2.dist-info/METADATA
pknulms-1.0.2.dist-info/RECORD
pknulms-1.0.2.dist-info/WHEEL
pknulms-1.0.2.dist-info/metadata.json
pknulms-1.0.2.dist-info/top_level.txt
