Metadata-Version: 2.0
Name: pknulms
Version: 1.0.2
Summary: Pukyong National University Smart-LMS Python client
Home-page: https://github.com/hallazzang/pknulms-py
Author: Hanjun Kim
Author-email: hallazzang@gmail.com
License: MIT
Platform: any
Classifier: Operating System :: OS Independent
Classifier: Programming Language :: Python
Classifier: Programming Language :: Python :: 2.6
Classifier: Programming Language :: Python :: 2.7
Classifier: Programming Language :: Python :: 3
Classifier: Programming Language :: Python :: 3.4
Classifier: Programming Language :: Python :: 3.5
Classifier: Programming Language :: Python :: 3.6
Classifier: Programming Language :: Python :: 3.7
Classifier: Topic :: Software Development :: Libraries :: Python Modules
Requires-Dist: requests
